MANIFEST.in
README.rst
setup.cfg
setup.py
sphinxcontrib/__init__.py
sphinxcontrib/autorun2.py
sphinxcontrib_autorun2.egg-info/PKG-INFO
sphinxcontrib_autorun2.egg-info/SOURCES.txt
sphinxcontrib_autorun2.egg-info/dependency_links.txt
sphinxcontrib_autorun2.egg-info/namespace_packages.txt
sphinxcontrib_autorun2.egg-info/not-zip-safe
sphinxcontrib_autorun2.egg-info/requires.txt
sphinxcontrib_autorun2.egg-info/top_level.txt