Metadata-Version: 1.0
Name: sphinxcontrib-autorun2
Version: 0.1-20140415
Summary: Sphinx extension autorun
Home-page: http://bitbucket.org/wolever/sphinx-contrib
Author: David Wolever
Author-email: david@wolever.net
License: BSD
Download-URL: http://pypi.python.org/pypi/sphinxcontrib-autorun2
Platform: any
Classifier: Development Status :: 4 - Beta
Classifier: Environment :: Console
Classifier: Environment :: Web Environment
Classifier: Intended Audience :: Developers
Classifier: License :: OSI Approved :: BSD License
Classifier: Operating System :: OS Independent
Classifier: Programming Language :: Python
Classifier: Topic :: Documentation
Classifier: Topic :: Utilities
